MANIFEST.in
README.md
setup.py
Orange3_Tarantool.egg-info/PKG-INFO
Orange3_Tarantool.egg-info/SOURCES.txt
Orange3_Tarantool.egg-info/dependency_links.txt
Orange3_Tarantool.egg-info/entry_points.txt
Orange3_Tarantool.egg-info/not-zip-safe
Orange3_Tarantool.egg-info/requires.txt
Orange3_Tarantool.egg-info/top_level.txt
rvncerr/orange3/tarantool/widgets/__init__.py
rvncerr/orange3/tarantool/widgets/connection.py
rvncerr/orange3/tarantool/widgets/correlation.py
rvncerr/orange3/tarantool/widgets/index.py
rvncerr/orange3/tarantool/widgets/lua.py
rvncerr/orange3/tarantool/widgets/partial.py
rvncerr/orange3/tarantool/widgets/schema.py
rvncerr/orange3/tarantool/widgets/select.py
rvncerr/orange3/tarantool/widgets/space.py
rvncerr/orange3/tarantool/widgets/timer.py
rvncerr/orange3/tarantool/widgets/tuple.py
rvncerr/orange3/tarantool/widgets/icons/category.svg
rvncerr/orange3/tarantool/widgets/icons/correlation.svg
rvncerr/orange3/tarantool/widgets/icons/index.svg
rvncerr/orange3/tarantool/widgets/icons/lua.svg
rvncerr/orange3/tarantool/widgets/icons/partial.svg
rvncerr/orange3/tarantool/widgets/icons/schema.svg
rvncerr/orange3/tarantool/widgets/icons/select.svg
rvncerr/orange3/tarantool/widgets/icons/space.svg
rvncerr/orange3/tarantool/widgets/icons/tarantool.svg
rvncerr/orange3/tarantool/widgets/icons/timer.svg
rvncerr/orange3/tarantool/widgets/icons/tuple.svg
rvncerr/orange3/tarantool/widgets/lua/orange.lua