Metadata-Version: 1.0
Name: Orange3-Tarantool
Version: 0.0.1a9
Summary: Tarantool Connector for Orange3.
Home-page: https://github.com/rvncerr/orange3-tarantool
Author: Dmitriy Kalugin-Balashov
Author-email: rvncerr@rvncerr.org
License: GPL
Keywords: orange3 add-on
Platform: UNKNOWN
